cdippy/__init__.py
cdippy/cdippy.py
cdippy/cli.py
cdippy/location.py
cdippy/mobile.py
cdippy/nchashes.py
cdippy/ncstats.py
cdippy/ndbc.py
cdippy/stndata.py
cdippy/timestamp_utils.py
cdippy/url_utils.py
cdippy/utils.py
cdippy-0.3.0.dist-info/AUTHORS.rst
cdippy-0.3.0.dist-info/LICENSE
cdippy-0.3.0.dist-info/METADATA
cdippy-0.3.0.dist-info/WHEEL
cdippy-0.3.0.dist-info/entry_points.txt
cdippy-0.3.0.dist-info/top_level.txt
cdippy-0.3.0.dist-info/RECORD
