Metadata-Version: 2.1
Name: cdippy
Version: 0.3.0
Summary: CDIPpy handles access to CDIP NetCDF data files
Home-page: https://github.com/wdar/cdippy
Author: Darren Wright
Author-email: darren@cdip.ucsd.edu
License: BSD license
Keywords: cdippy
Platform: UNKNOWN
Classifier: Development Status :: 2 - Pre-Alpha
Classifier: Intended Audience :: Developers
Classifier: License :: OSI Approved :: BSD License
Classifier: Natural Language :: English
Classifier: Programming Language :: Python :: 2
Classifier: Programming Language :: Python :: 2.7
Classifier: Programming Language :: Python :: 3
Classifier: Programming Language :: Python :: 3.4
Classifier: Programming Language :: Python :: 3.5
Classifier: Programming Language :: Python :: 3.6
Classifier: Programming Language :: Python :: 3.7
Requires-Dist: Click (>=6.0)
